Metadata-Version: 1.0
Name: qobs
Version: 0.0.3
Summary: self module for quickly uploading or downloading folders from ali oss
Home-page: UNKNOWN
Author: zwy
Author-email: zuowangyang@foxmail.com
License: MIT License
Keywords: obs,huaweiyun
Platform: any
